pynchon/__init__.py
pynchon/__main__.py
pynchon/_version.py
pynchon/annotate.py
pynchon/app.py
pynchon/base.py
pynchon/bin.py
pynchon/constants.py
pynchon/core.py
pynchon/events.py
pynchon/tagging.py
pynchon/testing.py
pynchon/abcs/__init__.py
pynchon/abcs/attrdict.py
pynchon/abcs/config.py
pynchon/abcs/path.py
pynchon/abcs/visitor.py
pynchon/api/__init__.py
pynchon/api/pynchon.py
pynchon/api/render.py
pynchon/api/git/__init__.py
pynchon/api/parsers/__init__.py
pynchon/api/project/__init__.py
pynchon/cli/__init__.py
pynchon/cli/common.py
pynchon/cli/options.py
pynchon/codemod/__init__.py
pynchon/codemod/commands/__init__.py
pynchon/codemod/commands/docstrings/__init__.py
pynchon/codemod/commands/docstrings/base.py
pynchon/codemod/commands/docstrings/javadoc.py
pynchon/codemod/commands/docstrings/simple.py
pynchon/config/__init__.py
pynchon/config/util.py
pynchon/models/__init__.py
pynchon/models/planner.py
pynchon/models/planning.py
pynchon/models/python.py
pynchon/models/plugins/__init__.py
pynchon/models/plugins/cli.py
pynchon/models/plugins/docker.py
pynchon/models/plugins/provider.py
pynchon/models/plugins/pynchon.py
pynchon/models/plugins/tool.py
pynchon/models/plugins/validators.py
pynchon/plugins/__init__.py
pynchon/plugins/__template__.py
pynchon/plugins/api.py
pynchon/plugins/cicd.py
pynchon/plugins/compose.py
pynchon/plugins/core.py
pynchon/plugins/deck.py
pynchon/plugins/dockerhub.py
pynchon/plugins/dot.py
pynchon/plugins/drawio.py
pynchon/plugins/fixme.py
pynchon/plugins/gen.py
pynchon/plugins/git.py
pynchon/plugins/github.py
pynchon/plugins/globals.py
pynchon/plugins/griffe.py
pynchon/plugins/hooks.py
pynchon/plugins/jinja.py
pynchon/plugins/makefile.py
pynchon/plugins/markdown.py
pynchon/plugins/mermaid.py
pynchon/plugins/mkdocs.py
pynchon/plugins/pandoc.py
pynchon/plugins/parse.py
pynchon/plugins/pattern.py
pynchon/plugins/plugins.py
pynchon/plugins/project.py
pynchon/plugins/release.py
pynchon/plugins/render.py
pynchon/plugins/rtd.py
pynchon-2025.3.20.17.28.dist-info/METADATA
pynchon-2025.3.20.17.28.dist-info/WHEEL
pynchon-2025.3.20.17.28.dist-info/entry_points.txt
pynchon-2025.3.20.17.28.dist-info/top_level.txt
pynchon-2025.3.20.17.28.dist-info/RECORD
