Metadata-Version: 2.4
Name: pynchon
Version: 2025.3.20.17.28
Summary: Autodocs for python projects
Home-page: https://github.com/elo-enterprises/pynchon/
Author: elo
Author-email: engineering@elo.enterprises
License: MIT
Project-URL: Documentation, https://github.com/elo-enterprises/pynchon/
Project-URL: Source, https://github.com/elo-enterprises/pynchon/
Project-URL: Download, https://github.com/elo-enterprises/pynchon/#files
Platform: any
Classifier: Programming Language :: Python
Requires-Python: >3.6
Requires-Dist: gripe>=2024.2.24.1.31
Requires-Dist: shil>=2024.5.30.18.30
Requires-Dist: shimport>=2023.7.11.23.36
Requires-Dist: fleks==2024.5.10.23.48
Requires-Dist: memoization==0.4.0
Requires-Dist: multipledispatch==0.6.0
Requires-Dist: pygments
Requires-Dist: pyjson5==1.6.1
Requires-Dist: marko==2.0.0
Requires-Dist: pyyaml
Requires-Dist: trogon
Requires-Dist: tomli_w==1.0.0
Requires-Dist: tomli
Requires-Dist: griffe==0.23.0
Requires-Dist: mccabe==0.7.0
Requires-Dist: Jinja2==3.1.2
Requires-Dist: grip==4.6.1
Requires-Dist: psutil==5.9.5
Requires-Dist: mkdocs>=1.5.3
Requires-Dist: mkdocs-material==9.5.3
Requires-Dist: beautifulsoup4==4.12.3
Provides-Extra: dev
Requires-Dist: IPython; extra == "dev"
Provides-Extra: testing
Requires-Dist: IPython; extra == "testing"
Requires-Dist: tox; extra == "testing"
Requires-Dist: pytest; extra == "testing"
Requires-Dist: pytest-cov; extra == "testing"
Requires-Dist: mock; extra == "testing"
Requires-Dist: flake8==5.0.4; extra == "testing"
Provides-Extra: lint
Requires-Dist: tox; extra == "lint"
Provides-Extra: publish
Requires-Dist: twine; extra == "publish"
